contracts/__init__.py
contracts/backported.py
contracts/docstring_parsing.py
contracts/enabling.py
contracts/inspection.py
contracts/interface.py
contracts/main.py
contracts/main_actual.py
contracts/metaclass.py
contracts/pyparsing_utils.py
contracts/syntax.py
contracts/test_registrar.py
contracts/utils.py
contracts/library/__init__.py
contracts/library/arithmetic.py
contracts/library/array.py
contracts/library/array_ops.py
contracts/library/attributes.py
contracts/library/collection.py
contracts/library/comparison.py
contracts/library/compositions.py
contracts/library/datetime_tz.py
contracts/library/dicts.py
contracts/library/dummy.py
contracts/library/extensions.py
contracts/library/files.py
contracts/library/isinstance_imp.py
contracts/library/lists.py
contracts/library/map.py
contracts/library/method.py
contracts/library/miscellaneous_aliases.py
contracts/library/scoped_variables.py
contracts/library/separate_context.py
contracts/library/seq.py
contracts/library/sets.py
contracts/library/simple_values.py
contracts/library/strings.py
contracts/library/suggester.py
contracts/library/tuple.py
contracts/library/types_misc.py
contracts/library/variables.py
contracts/testing/__init__.py
contracts/testing/array_extended_test.py
contracts/testing/friendliness_statistics.py
contracts/testing/test_class_contracts.py
contracts/testing/test_decorator.py
contracts/testing/test_docstring_parsing.py
contracts/testing/test_idioms.py
contracts/testing/test_meta.py
contracts/testing/test_multiple.py
contracts/testing/test_new_contract.py
contracts/testing/test_particulars.py
contracts/testing/test_pickling.py
contracts/testing/test_simple.py
contracts/testing/test_unicode_literals.py
contracts/testing/utils.py
contracts/testing/library/__init__.py
contracts/testing/library/arithmetic_tc.py
contracts/testing/library/array_elements_tc.py
contracts/testing/library/array_tc.py
contracts/testing/library/attr_tc.py
contracts/testing/library/collection_tc.py
PyContracts_mirror-2.0.1.17.dist-info/LICENSE.txt
PyContracts_mirror-2.0.1.17.dist-info/METADATA
PyContracts_mirror-2.0.1.17.dist-info/WHEEL
PyContracts_mirror-2.0.1.17.dist-info/top_level.txt
PyContracts_mirror-2.0.1.17.dist-info/RECORD
