Metadata-Version: 2.1
Name: PyContracts-mirror
Version: 2.0.1.17
Summary: INCOMPATIBLE FORK OF CURRENT PYCONTRACTS ON GITHUBThe version on pypi is stale, this is a fork that is updated from github andwith added support for jax. No guarantee that this will be kept up to date, or developed furtheror kept compatible with the original.See the original repo here: http://andreacensi.github.com/contracts/
Home-page: 
Download-URL: 
Author: xivarri
Author-email: xamvolagis@gmail.com
License: LGPL
Keywords: type checking,value checking,contracts
Classifier: Development Status :: 5 - Production/Stable
Classifier: Intended Audience :: Developers
Classifier: License :: OSI Approved :: GNU Library or Lesser General Public License (LGPL)
Classifier: Topic :: Software Development :: Quality Assurance
Classifier: Topic :: Software Development :: Documentation
Classifier: Topic :: Software Development :: Testing
Classifier: Programming Language :: Python :: 2.7
Classifier: Programming Language :: Python :: 3
Classifier: Programming Language :: Python :: 3.4
Classifier: Programming Language :: Python :: 3.5
Classifier: Programming Language :: Python :: 3.6
License-File: LICENSE.txt
Requires-Dist: pyparsing
Requires-Dist: decorator
Requires-Dist: six
Requires-Dist: future
